iron_falcon/__init__.py
iron_falcon/middleware.py
iron_falcon/resource.py
iron_falcon/utils.py
iron_falcon-1.2.2a0.dist-info/METADATA
iron_falcon-1.2.2a0.dist-info/WHEEL
iron_falcon-1.2.2a0.dist-info/top_level.txt
iron_falcon-1.2.2a0.dist-info/RECORD
